{
  "query": "Craftsman wrench",
  "brand": "craftsman",
  "prices": [
    {
      "store": "Walmart Canada",
      "storeLogo": "walmart",
      "price": 22.69,
      "inStock": true,
      "url": "https://www.walmart.ca/en/ip/CRAFTSMAN-Adjustable-Wrench-18-Inch-CMMT81626/0TEP23RRLG3S?classType=REGULAR",
      "name": "CRAFTSMAN Adjustable Wrench, 18-Inch (CMMT81626)",
      "image": "https://i5.walmartimages.com/asr/c0204f73-b3af-4756-912a-bcee57a236fb.dafc64e2fb3d3d67308923a83341f144.jpeg",
      "lastUpdated": "2026-04-14T09:21:48.697Z"
    },
    {
      "store": "Amazon Canada",
      "storeLogo": "amazon",
      "lastUpdated": "2026-04-14T09:21:48.697Z",
      "price": 0,
      "inStock": true,
      "url": "https://www.amazon.ca/s?k=Craftsman%20wrench&i=tools&tag=canadiantool-20",
      "name": "Search \"Craftsman wrench\" on Amazon Canada",
      "checkManually": true
    },
    {
      "store": "Canadian Tire",
      "storeLogo": "canadiantire",
      "lastUpdated": "2026-04-14T09:21:48.697Z",
      "price": 0,
      "inStock": true,
      "url": "https://www.canadiantire.ca/en/search-results.html?q=Craftsman%20wrench",
      "name": "Search \"Craftsman wrench\" on Canadian Tire",
      "checkManually": true
    },
    {
      "store": "Home Depot Canada",
      "storeLogo": "homedepot",
      "lastUpdated": "2026-04-14T09:21:48.697Z",
      "price": 0,
      "inStock": false,
      "url": "https://www.homedepot.ca/search?q=Craftsman%20wrench",
      "name": "Craftsman not sold at Home Depot Canada",
      "notCarried": true
    },
    {
      "store": "RONA",
      "storeLogo": "rona",
      "lastUpdated": "2026-04-14T09:21:48.697Z",
      "price": 0,
      "inStock": false,
      "url": "https://www.rona.ca/en/search?q=Craftsman%20wrench",
      "name": "Craftsman not sold at RONA",
      "notCarried": true
    },
    {
      "store": "Princess Auto",
      "storeLogo": "princessauto",
      "lastUpdated": "2026-04-14T09:21:48.697Z",
      "price": 0,
      "inStock": false,
      "url": "https://www.princessauto.com/en/search#q=Craftsman%20wrench",
      "name": "Craftsman not sold at Princess Auto",
      "notCarried": true
    }
  ],
  "fetchedAt": "2026-04-14T09:21:48.697Z"
}