[
  {
    "query": "Milwaukee M18 drill",
    "slug": "milwaukee-m18-drill",
    "brand": "milwaukee",
    "lowestPrice": null,
    "lowestStore": null,
    "discount": null,
    "priceCount": 0,
    "fetchedAt": "2026-05-10T09:27:13.017Z"
  },
  {
    "query": "Milwaukee M18 circular saw",
    "slug": "milwaukee-m18-circular-saw",
    "brand": "milwaukee",
    "lowestPrice": null,
    "lowestStore": null,
    "discount": null,
    "priceCount": 0,
    "fetchedAt": "2026-05-10T09:27:29.219Z"
  },
  {
    "query": "Milwaukee M12",
    "slug": "milwaukee-m12",
    "brand": "milwaukee",
    "lowestPrice": null,
    "lowestStore": null,
    "discount": null,
    "priceCount": 0,
    "fetchedAt": "2026-05-10T09:27:45.421Z"
  },
  {
    "query": "Milwaukee M18 impact driver",
    "slug": "milwaukee-m18-impact-driver",
    "brand": "milwaukee",
    "lowestPrice": null,
    "lowestStore": null,
    "discount": null,
    "priceCount": 0,
    "fetchedAt": "2026-05-10T09:28:01.624Z"
  },
  {
    "query": "Milwaukee Packout",
    "slug": "milwaukee-packout",
    "brand": "milwaukee packout",
    "lowestPrice": null,
    "lowestStore": null,
    "discount": null,
    "priceCount": 0,
    "fetchedAt": "2026-05-10T09:28:17.827Z"
  },
  {
    "query": "Milwaukee M18 grinder",
    "slug": "milwaukee-m18-grinder",
    "brand": "milwaukee",
    "lowestPrice": null,
    "lowestStore": null,
    "discount": null,
    "priceCount": 0,
    "fetchedAt": "2026-05-10T09:28:34.028Z"
  },
  {
    "query": "DeWalt 20V drill",
    "slug": "dewalt-20v-drill",
    "brand": "dewalt",
    "lowestPrice": null,
    "lowestStore": null,
    "discount": null,
    "priceCount": 0,
    "fetchedAt": "2026-05-10T09:28:50.231Z"
  },
  {
    "query": "DeWalt circular saw",
    "slug": "dewalt-circular-saw",
    "brand": "dewalt",
    "lowestPrice": null,
    "lowestStore": null,
    "discount": null,
    "priceCount": 0,
    "fetchedAt": "2026-05-10T09:29:06.432Z"
  },
  {
    "query": "DeWalt table saw",
    "slug": "dewalt-table-saw",
    "brand": "dewalt",
    "lowestPrice": null,
    "lowestStore": null,
    "discount": null,
    "priceCount": 0,
    "fetchedAt": "2026-05-10T09:29:22.634Z"
  },
  {
    "query": "DeWalt impact driver",
    "slug": "dewalt-impact-driver",
    "brand": "dewalt",
    "lowestPrice": null,
    "lowestStore": null,
    "discount": null,
    "priceCount": 0,
    "fetchedAt": "2026-05-10T09:29:38.836Z"
  },
  {
    "query": "DeWalt jigsaw",
    "slug": "dewalt-jigsaw",
    "brand": "dewalt",
    "lowestPrice": null,
    "lowestStore": null,
    "discount": null,
    "priceCount": 0,
    "fetchedAt": "2026-05-10T09:29:55.039Z"
  },
  {
    "query": "Makita 18V drill",
    "slug": "makita-18v-drill",
    "brand": "makita",
    "lowestPrice": null,
    "lowestStore": null,
    "discount": null,
    "priceCount": 0,
    "fetchedAt": "2026-05-10T09:30:11.240Z"
  },
  {
    "query": "Makita impact driver",
    "slug": "makita-impact-driver",
    "brand": "makita",
    "lowestPrice": null,
    "lowestStore": null,
    "discount": null,
    "priceCount": 0,
    "fetchedAt": "2026-05-10T09:30:27.442Z"
  },
  {
    "query": "Makita circular saw",
    "slug": "makita-circular-saw",
    "brand": "makita",
    "lowestPrice": null,
    "lowestStore": null,
    "discount": null,
    "priceCount": 0,
    "fetchedAt": "2026-05-10T09:30:43.643Z"
  },
  {
    "query": "Mastercraft drill",
    "slug": "mastercraft-drill",
    "brand": "mastercraft",
    "lowestPrice": null,
    "lowestStore": null,
    "discount": null,
    "priceCount": 0,
    "fetchedAt": "2026-05-10T09:30:45.012Z"
  },
  {
    "query": "Mastercraft socket set",
    "slug": "mastercraft-socket-set",
    "brand": "mastercraft",
    "lowestPrice": null,
    "lowestStore": null,
    "discount": null,
    "priceCount": 0,
    "fetchedAt": "2026-05-10T09:30:46.330Z"
  },
  {
    "query": "Mastercraft wrench set",
    "slug": "mastercraft-wrench-set",
    "brand": "mastercraft",
    "lowestPrice": null,
    "lowestStore": null,
    "discount": null,
    "priceCount": 0,
    "fetchedAt": "2026-05-10T09:30:47.660Z"
  },
  {
    "query": "Maximum drill",
    "slug": "maximum-drill",
    "brand": "maximum",
    "lowestPrice": null,
    "lowestStore": null,
    "discount": null,
    "priceCount": 0,
    "fetchedAt": "2026-05-10T09:30:48.978Z"
  },
  {
    "query": "Maximum circular saw",
    "slug": "maximum-circular-saw",
    "brand": "maximum",
    "lowestPrice": null,
    "lowestStore": null,
    "discount": null,
    "priceCount": 0,
    "fetchedAt": "2026-05-10T09:30:50.366Z"
  },
  {
    "query": "Ryobi 18V drill",
    "slug": "ryobi-18v-drill",
    "brand": "ryobi",
    "lowestPrice": null,
    "lowestStore": null,
    "discount": null,
    "priceCount": 0,
    "fetchedAt": "2026-05-10T09:31:06.568Z"
  },
  {
    "query": "Ryobi circular saw",
    "slug": "ryobi-circular-saw",
    "brand": "ryobi",
    "lowestPrice": null,
    "lowestStore": null,
    "discount": null,
    "priceCount": 0,
    "fetchedAt": "2026-05-10T09:31:22.771Z"
  },
  {
    "query": "Husky wrench set",
    "slug": "husky-wrench-set",
    "brand": "husky",
    "lowestPrice": null,
    "lowestStore": null,
    "discount": null,
    "priceCount": 0,
    "fetchedAt": "2026-05-10T09:31:38.972Z"
  },
  {
    "query": "Husky socket set",
    "slug": "husky-socket-set",
    "brand": "husky",
    "lowestPrice": null,
    "lowestStore": null,
    "discount": null,
    "priceCount": 0,
    "fetchedAt": "2026-05-10T09:31:55.174Z"
  },
  {
    "query": "Husky tool set",
    "slug": "husky-tool-set",
    "brand": "husky",
    "lowestPrice": null,
    "lowestStore": null,
    "discount": null,
    "priceCount": 0,
    "fetchedAt": "2026-05-10T09:32:11.375Z"
  },
  {
    "query": "Stanley screwdriver set",
    "slug": "stanley-screwdriver-set",
    "brand": "stanley",
    "lowestPrice": null,
    "lowestStore": null,
    "discount": null,
    "priceCount": 0,
    "fetchedAt": "2026-05-10T09:32:12.976Z"
  },
  {
    "query": "Stanley hand tools",
    "slug": "stanley-hand-tools",
    "brand": "stanley",
    "lowestPrice": null,
    "lowestStore": null,
    "discount": null,
    "priceCount": 0,
    "fetchedAt": "2026-05-10T09:32:14.539Z"
  },
  {
    "query": "Craftsman socket set",
    "slug": "craftsman-socket-set",
    "brand": "craftsman",
    "lowestPrice": null,
    "lowestStore": null,
    "discount": null,
    "priceCount": 0,
    "fetchedAt": "2026-05-10T09:32:15.992Z"
  },
  {
    "query": "Craftsman wrench",
    "slug": "craftsman-wrench",
    "brand": "craftsman",
    "lowestPrice": null,
    "lowestStore": null,
    "discount": null,
    "priceCount": 0,
    "fetchedAt": "2026-05-10T09:32:17.494Z"
  },
  {
    "query": "GearWrench ratchet",
    "slug": "gearwrench-ratchet",
    "brand": "gearwrench",
    "lowestPrice": null,
    "lowestStore": null,
    "discount": null,
    "priceCount": 0,
    "fetchedAt": "2026-05-10T09:32:18.935Z"
  },
  {
    "query": "GearWrench socket set",
    "slug": "gearwrench-socket-set",
    "brand": "gearwrench",
    "lowestPrice": null,
    "lowestStore": null,
    "discount": null,
    "priceCount": 0,
    "fetchedAt": "2026-05-10T09:32:20.257Z"
  },
  {
    "query": "Bosch drill",
    "slug": "bosch-drill",
    "brand": "bosch",
    "lowestPrice": null,
    "lowestStore": null,
    "discount": null,
    "priceCount": 0,
    "fetchedAt": "2026-05-10T09:32:36.458Z"
  },
  {
    "query": "Bosch laser level",
    "slug": "bosch-laser-level",
    "brand": "bosch",
    "lowestPrice": null,
    "lowestStore": null,
    "discount": null,
    "priceCount": 0,
    "fetchedAt": "2026-05-10T09:32:52.659Z"
  },
  {
    "query": "Powerfist air compressor",
    "slug": "powerfist-air-compressor",
    "brand": "powerfist",
    "lowestPrice": null,
    "lowestStore": null,
    "discount": null,
    "priceCount": 0,
    "fetchedAt": "2026-05-10T09:32:54.033Z"
  },
  {
    "query": "Powerfist socket set",
    "slug": "powerfist-socket-set",
    "brand": "powerfist",
    "lowestPrice": null,
    "lowestStore": null,
    "discount": null,
    "priceCount": 0,
    "fetchedAt": "2026-05-10T09:32:55.365Z"
  },
  {
    "query": "Lincoln grease gun",
    "slug": "lincoln-grease-gun",
    "brand": "lincoln",
    "lowestPrice": null,
    "lowestStore": null,
    "discount": null,
    "priceCount": 0,
    "fetchedAt": "2026-05-10T09:32:56.761Z"
  },
  {
    "query": "Lincoln electric welder",
    "slug": "lincoln-electric-welder",
    "brand": "lincoln electric",
    "lowestPrice": null,
    "lowestStore": null,
    "discount": null,
    "priceCount": 0,
    "fetchedAt": "2026-05-10T09:32:58.092Z"
  },
  {
    "query": "Fluke multimeter",
    "slug": "fluke-multimeter",
    "brand": "fluke",
    "lowestPrice": null,
    "lowestStore": null,
    "discount": null,
    "priceCount": 0,
    "fetchedAt": "2026-05-10T09:32:59.321Z"
  },
  {
    "query": "Jobmate drill",
    "slug": "jobmate-drill",
    "brand": "jobmate",
    "lowestPrice": null,
    "lowestStore": null,
    "discount": null,
    "priceCount": 0,
    "fetchedAt": "2026-05-10T09:33:00.648Z"
  },
  {
    "query": "Jobmate socket set",
    "slug": "jobmate-socket-set",
    "brand": "jobmate",
    "lowestPrice": null,
    "lowestStore": null,
    "discount": null,
    "priceCount": 0,
    "fetchedAt": "2026-05-10T09:33:02.046Z"
  },
  {
    "query": "Hart drill",
    "slug": "hart-drill",
    "brand": "hart",
    "lowestPrice": null,
    "lowestStore": null,
    "discount": null,
    "priceCount": 0,
    "fetchedAt": "2026-05-10T09:33:03.565Z"
  },
  {
    "query": "Hart impact driver",
    "slug": "hart-impact-driver",
    "brand": "hart",
    "lowestPrice": null,
    "lowestStore": null,
    "discount": null,
    "priceCount": 0,
    "fetchedAt": "2026-05-10T09:33:04.963Z"
  },
  {
    "query": "Greenworks lawn mower",
    "slug": "greenworks-lawn-mower",
    "brand": "greenworks",
    "lowestPrice": null,
    "lowestStore": null,
    "discount": null,
    "priceCount": 0,
    "fetchedAt": "2026-05-10T09:33:21.165Z"
  },
  {
    "query": "Greenworks 40V",
    "slug": "greenworks-40v",
    "brand": "greenworks",
    "lowestPrice": null,
    "lowestStore": null,
    "discount": null,
    "priceCount": 0,
    "fetchedAt": "2026-05-10T09:33:37.365Z"
  },
  {
    "query": "Dremel rotary tool",
    "slug": "dremel-rotary-tool",
    "brand": "dremel",
    "lowestPrice": null,
    "lowestStore": null,
    "discount": null,
    "priceCount": 0,
    "fetchedAt": "2026-05-10T09:33:53.567Z"
  },
  {
    "query": "Dremel kit",
    "slug": "dremel-kit",
    "brand": "dremel",
    "lowestPrice": null,
    "lowestStore": null,
    "discount": null,
    "priceCount": 0,
    "fetchedAt": "2026-05-10T09:34:09.768Z"
  },
  {
    "query": "Leatherman multi-tool",
    "slug": "leatherman-multi-tool",
    "brand": "leatherman",
    "lowestPrice": null,
    "lowestStore": null,
    "discount": null,
    "priceCount": 0,
    "fetchedAt": "2026-05-10T09:34:11.091Z"
  },
  {
    "query": "Worx drill",
    "slug": "worx-drill",
    "brand": "worx",
    "lowestPrice": null,
    "lowestStore": null,
    "discount": null,
    "priceCount": 0,
    "fetchedAt": "2026-05-10T09:34:12.781Z"
  },
  {
    "query": "Worx circular saw",
    "slug": "worx-circular-saw",
    "brand": "worx",
    "lowestPrice": null,
    "lowestStore": null,
    "discount": null,
    "priceCount": 0,
    "fetchedAt": "2026-05-10T09:34:14.415Z"
  },
  {
    "query": "RIDGID shop vac",
    "slug": "ridgid-shop-vac",
    "brand": "ridgid",
    "lowestPrice": null,
    "lowestStore": null,
    "discount": null,
    "priceCount": 0,
    "fetchedAt": "2026-05-10T09:34:30.619Z"
  },
  {
    "query": "RIDGID wet dry vac",
    "slug": "ridgid-wet-dry-vac",
    "brand": "ridgid",
    "lowestPrice": null,
    "lowestStore": null,
    "discount": null,
    "priceCount": 0,
    "fetchedAt": "2026-05-10T09:34:46.821Z"
  },
  {
    "query": "EGO lawn mower",
    "slug": "ego-lawn-mower",
    "brand": "ego",
    "lowestPrice": null,
    "lowestStore": null,
    "discount": null,
    "priceCount": 0,
    "fetchedAt": "2026-05-10T09:35:03.022Z"
  },
  {
    "query": "EGO 56V",
    "slug": "ego-56v",
    "brand": "ego",
    "lowestPrice": null,
    "lowestStore": null,
    "discount": null,
    "priceCount": 0,
    "fetchedAt": "2026-05-10T09:35:19.223Z"
  },
  {
    "query": "Klein screwdriver set",
    "slug": "klein-screwdriver-set",
    "brand": "klein",
    "lowestPrice": null,
    "lowestStore": null,
    "discount": null,
    "priceCount": 0,
    "fetchedAt": "2026-05-10T09:35:35.425Z"
  },
  {
    "query": "Klein pliers",
    "slug": "klein-pliers",
    "brand": "klein",
    "lowestPrice": null,
    "lowestStore": null,
    "discount": null,
    "priceCount": 0,
    "fetchedAt": "2026-05-10T09:35:51.627Z"
  }
]