[
  {
    "query": "Milwaukee M18 drill",
    "slug": "milwaukee-m18-drill",
    "brand": "milwaukee",
    "lowestPrice": null,
    "lowestStore": null,
    "discount": null,
    "priceCount": 0,
    "fetchedAt": "2026-06-13T10:26:53.207Z"
  },
  {
    "query": "Milwaukee M18 circular saw",
    "slug": "milwaukee-m18-circular-saw",
    "brand": "milwaukee",
    "lowestPrice": null,
    "lowestStore": null,
    "discount": null,
    "priceCount": 0,
    "fetchedAt": "2026-06-13T10:27:09.410Z"
  },
  {
    "query": "Milwaukee M12",
    "slug": "milwaukee-m12",
    "brand": "milwaukee",
    "lowestPrice": null,
    "lowestStore": null,
    "discount": null,
    "priceCount": 0,
    "fetchedAt": "2026-06-13T10:27:25.612Z"
  },
  {
    "query": "Milwaukee M18 impact driver",
    "slug": "milwaukee-m18-impact-driver",
    "brand": "milwaukee",
    "lowestPrice": null,
    "lowestStore": null,
    "discount": null,
    "priceCount": 0,
    "fetchedAt": "2026-06-13T10:27:41.814Z"
  },
  {
    "query": "Milwaukee Packout",
    "slug": "milwaukee-packout",
    "brand": "milwaukee packout",
    "lowestPrice": null,
    "lowestStore": null,
    "discount": null,
    "priceCount": 0,
    "fetchedAt": "2026-06-13T10:27:58.016Z"
  },
  {
    "query": "Milwaukee M18 grinder",
    "slug": "milwaukee-m18-grinder",
    "brand": "milwaukee",
    "lowestPrice": null,
    "lowestStore": null,
    "discount": null,
    "priceCount": 0,
    "fetchedAt": "2026-06-13T10:28:14.218Z"
  },
  {
    "query": "DeWalt 20V drill",
    "slug": "dewalt-20v-drill",
    "brand": "dewalt",
    "lowestPrice": null,
    "lowestStore": null,
    "discount": null,
    "priceCount": 0,
    "fetchedAt": "2026-06-13T10:28:30.420Z"
  },
  {
    "query": "DeWalt circular saw",
    "slug": "dewalt-circular-saw",
    "brand": "dewalt",
    "lowestPrice": null,
    "lowestStore": null,
    "discount": null,
    "priceCount": 0,
    "fetchedAt": "2026-06-13T10:28:46.623Z"
  },
  {
    "query": "DeWalt table saw",
    "slug": "dewalt-table-saw",
    "brand": "dewalt",
    "lowestPrice": null,
    "lowestStore": null,
    "discount": null,
    "priceCount": 0,
    "fetchedAt": "2026-06-13T10:29:02.825Z"
  },
  {
    "query": "DeWalt impact driver",
    "slug": "dewalt-impact-driver",
    "brand": "dewalt",
    "lowestPrice": null,
    "lowestStore": null,
    "discount": null,
    "priceCount": 0,
    "fetchedAt": "2026-06-13T10:29:19.027Z"
  },
  {
    "query": "DeWalt jigsaw",
    "slug": "dewalt-jigsaw",
    "brand": "dewalt",
    "lowestPrice": null,
    "lowestStore": null,
    "discount": null,
    "priceCount": 0,
    "fetchedAt": "2026-06-13T10:29:35.230Z"
  },
  {
    "query": "Makita 18V drill",
    "slug": "makita-18v-drill",
    "brand": "makita",
    "lowestPrice": null,
    "lowestStore": null,
    "discount": null,
    "priceCount": 0,
    "fetchedAt": "2026-06-13T10:29:51.432Z"
  },
  {
    "query": "Makita impact driver",
    "slug": "makita-impact-driver",
    "brand": "makita",
    "lowestPrice": null,
    "lowestStore": null,
    "discount": null,
    "priceCount": 0,
    "fetchedAt": "2026-06-13T10:30:07.635Z"
  },
  {
    "query": "Makita circular saw",
    "slug": "makita-circular-saw",
    "brand": "makita",
    "lowestPrice": null,
    "lowestStore": null,
    "discount": null,
    "priceCount": 0,
    "fetchedAt": "2026-06-13T10:30:23.837Z"
  },
  {
    "query": "Mastercraft drill",
    "slug": "mastercraft-drill",
    "brand": "mastercraft",
    "lowestPrice": null,
    "lowestStore": null,
    "discount": null,
    "priceCount": 0,
    "fetchedAt": "2026-06-13T10:30:25.328Z"
  },
  {
    "query": "Mastercraft socket set",
    "slug": "mastercraft-socket-set",
    "brand": "mastercraft",
    "lowestPrice": null,
    "lowestStore": null,
    "discount": null,
    "priceCount": 0,
    "fetchedAt": "2026-06-13T10:30:26.789Z"
  },
  {
    "query": "Mastercraft wrench set",
    "slug": "mastercraft-wrench-set",
    "brand": "mastercraft",
    "lowestPrice": null,
    "lowestStore": null,
    "discount": null,
    "priceCount": 0,
    "fetchedAt": "2026-06-13T10:30:28.190Z"
  },
  {
    "query": "Maximum drill",
    "slug": "maximum-drill",
    "brand": "maximum",
    "lowestPrice": null,
    "lowestStore": null,
    "discount": null,
    "priceCount": 0,
    "fetchedAt": "2026-06-13T10:30:29.639Z"
  },
  {
    "query": "Maximum circular saw",
    "slug": "maximum-circular-saw",
    "brand": "maximum",
    "lowestPrice": null,
    "lowestStore": null,
    "discount": null,
    "priceCount": 0,
    "fetchedAt": "2026-06-13T10:30:31.085Z"
  },
  {
    "query": "Ryobi 18V drill",
    "slug": "ryobi-18v-drill",
    "brand": "ryobi",
    "lowestPrice": null,
    "lowestStore": null,
    "discount": null,
    "priceCount": 0,
    "fetchedAt": "2026-06-13T10:30:47.288Z"
  },
  {
    "query": "Ryobi circular saw",
    "slug": "ryobi-circular-saw",
    "brand": "ryobi",
    "lowestPrice": null,
    "lowestStore": null,
    "discount": null,
    "priceCount": 0,
    "fetchedAt": "2026-06-13T10:31:03.491Z"
  },
  {
    "query": "Husky wrench set",
    "slug": "husky-wrench-set",
    "brand": "husky",
    "lowestPrice": null,
    "lowestStore": null,
    "discount": null,
    "priceCount": 0,
    "fetchedAt": "2026-06-13T10:31:19.693Z"
  },
  {
    "query": "Husky socket set",
    "slug": "husky-socket-set",
    "brand": "husky",
    "lowestPrice": null,
    "lowestStore": null,
    "discount": null,
    "priceCount": 0,
    "fetchedAt": "2026-06-13T10:31:35.893Z"
  },
  {
    "query": "Husky tool set",
    "slug": "husky-tool-set",
    "brand": "husky",
    "lowestPrice": null,
    "lowestStore": null,
    "discount": null,
    "priceCount": 0,
    "fetchedAt": "2026-06-13T10:31:52.094Z"
  },
  {
    "query": "Stanley screwdriver set",
    "slug": "stanley-screwdriver-set",
    "brand": "stanley",
    "lowestPrice": null,
    "lowestStore": null,
    "discount": null,
    "priceCount": 0,
    "fetchedAt": "2026-06-13T10:31:54.140Z"
  },
  {
    "query": "Stanley hand tools",
    "slug": "stanley-hand-tools",
    "brand": "stanley",
    "lowestPrice": null,
    "lowestStore": null,
    "discount": null,
    "priceCount": 0,
    "fetchedAt": "2026-06-13T10:31:55.655Z"
  },
  {
    "query": "Craftsman socket set",
    "slug": "craftsman-socket-set",
    "brand": "craftsman",
    "lowestPrice": null,
    "lowestStore": null,
    "discount": null,
    "priceCount": 0,
    "fetchedAt": "2026-06-13T10:31:57.218Z"
  },
  {
    "query": "Craftsman wrench",
    "slug": "craftsman-wrench",
    "brand": "craftsman",
    "lowestPrice": null,
    "lowestStore": null,
    "discount": null,
    "priceCount": 0,
    "fetchedAt": "2026-06-13T10:31:58.808Z"
  },
  {
    "query": "GearWrench ratchet",
    "slug": "gearwrench-ratchet",
    "brand": "gearwrench",
    "lowestPrice": null,
    "lowestStore": null,
    "discount": null,
    "priceCount": 0,
    "fetchedAt": "2026-06-13T10:32:00.293Z"
  },
  {
    "query": "GearWrench socket set",
    "slug": "gearwrench-socket-set",
    "brand": "gearwrench",
    "lowestPrice": null,
    "lowestStore": null,
    "discount": null,
    "priceCount": 0,
    "fetchedAt": "2026-06-13T10:32:01.703Z"
  },
  {
    "query": "Bosch drill",
    "slug": "bosch-drill",
    "brand": "bosch",
    "lowestPrice": null,
    "lowestStore": null,
    "discount": null,
    "priceCount": 0,
    "fetchedAt": "2026-06-13T10:32:17.904Z"
  },
  {
    "query": "Bosch laser level",
    "slug": "bosch-laser-level",
    "brand": "bosch",
    "lowestPrice": null,
    "lowestStore": null,
    "discount": null,
    "priceCount": 0,
    "fetchedAt": "2026-06-13T10:32:34.104Z"
  },
  {
    "query": "Powerfist air compressor",
    "slug": "powerfist-air-compressor",
    "brand": "powerfist",
    "lowestPrice": null,
    "lowestStore": null,
    "discount": null,
    "priceCount": 0,
    "fetchedAt": "2026-06-13T10:32:35.627Z"
  },
  {
    "query": "Powerfist socket set",
    "slug": "powerfist-socket-set",
    "brand": "powerfist",
    "lowestPrice": null,
    "lowestStore": null,
    "discount": null,
    "priceCount": 0,
    "fetchedAt": "2026-06-13T10:32:36.923Z"
  },
  {
    "query": "Lincoln grease gun",
    "slug": "lincoln-grease-gun",
    "brand": "lincoln",
    "lowestPrice": null,
    "lowestStore": null,
    "discount": null,
    "priceCount": 0,
    "fetchedAt": "2026-06-13T10:32:38.369Z"
  },
  {
    "query": "Lincoln electric welder",
    "slug": "lincoln-electric-welder",
    "brand": "lincoln electric",
    "lowestPrice": null,
    "lowestStore": null,
    "discount": null,
    "priceCount": 0,
    "fetchedAt": "2026-06-13T10:32:39.665Z"
  },
  {
    "query": "Fluke multimeter",
    "slug": "fluke-multimeter",
    "brand": "fluke",
    "lowestPrice": null,
    "lowestStore": null,
    "discount": null,
    "priceCount": 0,
    "fetchedAt": "2026-06-13T10:32:40.880Z"
  },
  {
    "query": "Jobmate drill",
    "slug": "jobmate-drill",
    "brand": "jobmate",
    "lowestPrice": null,
    "lowestStore": null,
    "discount": null,
    "priceCount": 0,
    "fetchedAt": "2026-06-13T10:32:42.217Z"
  },
  {
    "query": "Jobmate socket set",
    "slug": "jobmate-socket-set",
    "brand": "jobmate",
    "lowestPrice": null,
    "lowestStore": null,
    "discount": null,
    "priceCount": 0,
    "fetchedAt": "2026-06-13T10:32:43.606Z"
  },
  {
    "query": "Hart drill",
    "slug": "hart-drill",
    "brand": "hart",
    "lowestPrice": null,
    "lowestStore": null,
    "discount": null,
    "priceCount": 0,
    "fetchedAt": "2026-06-13T10:32:45.336Z"
  },
  {
    "query": "Hart impact driver",
    "slug": "hart-impact-driver",
    "brand": "hart",
    "lowestPrice": null,
    "lowestStore": null,
    "discount": null,
    "priceCount": 0,
    "fetchedAt": "2026-06-13T10:32:46.807Z"
  },
  {
    "query": "Greenworks lawn mower",
    "slug": "greenworks-lawn-mower",
    "brand": "greenworks",
    "lowestPrice": null,
    "lowestStore": null,
    "discount": null,
    "priceCount": 0,
    "fetchedAt": "2026-06-13T10:33:03.009Z"
  },
  {
    "query": "Greenworks 40V",
    "slug": "greenworks-40v",
    "brand": "greenworks",
    "lowestPrice": null,
    "lowestStore": null,
    "discount": null,
    "priceCount": 0,
    "fetchedAt": "2026-06-13T10:33:19.209Z"
  },
  {
    "query": "Dremel rotary tool",
    "slug": "dremel-rotary-tool",
    "brand": "dremel",
    "lowestPrice": null,
    "lowestStore": null,
    "discount": null,
    "priceCount": 0,
    "fetchedAt": "2026-06-13T10:33:35.411Z"
  },
  {
    "query": "Dremel kit",
    "slug": "dremel-kit",
    "brand": "dremel",
    "lowestPrice": null,
    "lowestStore": null,
    "discount": null,
    "priceCount": 0,
    "fetchedAt": "2026-06-13T10:33:51.611Z"
  },
  {
    "query": "Leatherman multi-tool",
    "slug": "leatherman-multi-tool",
    "brand": "leatherman",
    "lowestPrice": null,
    "lowestStore": null,
    "discount": null,
    "priceCount": 0,
    "fetchedAt": "2026-06-13T10:33:52.906Z"
  },
  {
    "query": "Worx drill",
    "slug": "worx-drill",
    "brand": "worx",
    "lowestPrice": null,
    "lowestStore": null,
    "discount": null,
    "priceCount": 0,
    "fetchedAt": "2026-06-13T10:33:54.399Z"
  },
  {
    "query": "Worx circular saw",
    "slug": "worx-circular-saw",
    "brand": "worx",
    "lowestPrice": null,
    "lowestStore": null,
    "discount": null,
    "priceCount": 0,
    "fetchedAt": "2026-06-13T10:33:55.955Z"
  },
  {
    "query": "RIDGID shop vac",
    "slug": "ridgid-shop-vac",
    "brand": "ridgid",
    "lowestPrice": null,
    "lowestStore": null,
    "discount": null,
    "priceCount": 0,
    "fetchedAt": "2026-06-13T10:34:12.155Z"
  },
  {
    "query": "RIDGID wet dry vac",
    "slug": "ridgid-wet-dry-vac",
    "brand": "ridgid",
    "lowestPrice": null,
    "lowestStore": null,
    "discount": null,
    "priceCount": 0,
    "fetchedAt": "2026-06-13T10:34:28.357Z"
  },
  {
    "query": "EGO lawn mower",
    "slug": "ego-lawn-mower",
    "brand": "ego",
    "lowestPrice": null,
    "lowestStore": null,
    "discount": null,
    "priceCount": 0,
    "fetchedAt": "2026-06-13T10:34:44.559Z"
  },
  {
    "query": "EGO 56V",
    "slug": "ego-56v",
    "brand": "ego",
    "lowestPrice": null,
    "lowestStore": null,
    "discount": null,
    "priceCount": 0,
    "fetchedAt": "2026-06-13T10:35:00.762Z"
  },
  {
    "query": "Klein screwdriver set",
    "slug": "klein-screwdriver-set",
    "brand": "klein",
    "lowestPrice": null,
    "lowestStore": null,
    "discount": null,
    "priceCount": 0,
    "fetchedAt": "2026-06-13T10:35:16.965Z"
  },
  {
    "query": "Klein pliers",
    "slug": "klein-pliers",
    "brand": "klein",
    "lowestPrice": null,
    "lowestStore": null,
    "discount": null,
    "priceCount": 0,
    "fetchedAt": "2026-06-13T10:35:33.168Z"
  }
]